{
  "npc_id": 2890,
  "rare_table": true,
  "drops": [
    {
      "item": 526,
      "minimum": 1,
      "maximum": 1,
      "type": "ALWAYS"
    },
    {
      "item": 249,
      "minimum": 1,
      "maximum": 2,
      "type": "COMMON"
    },
    {
      "item": 251,
      "minimum": 1,
      "maximum": 2,
      "type": "COMMON"
    },
    {
      "item": 253,
      "minimum": 1,
      "maximum": 2,
      "type": "COMMON"
    },
    {
      "item": 255,
      "minimum": 1,
      "maximum": 2,
      "type": "COMMON"
    },
    {
      "item": 259,
      "minimum": 1,
      "maximum": 2,
      "type": "UNCOMMON"
    },
    {
      "item": 261,
      "minimum": 1,
      "maximum": 2,
      "type": "UNCOMMON"
    },
    {
      "item": 263,
      "minimum": 1,
      "maximum": 2,
      "type": "UNCOMMON"
    },
    {
      "item": 265,
      "minimum": 1,
      "maximum": 2,
      "type": "UNCOMMON"
    },
    {
      "item": 267,
      "minimum": 1,
      "maximum": 2,
      "type": "UNCOMMON"
    },
    {
      "item": 257,
      "minimum": 1,
      "maximum": 2,
      "type": "RARE"
    },
    {
      "item": 2481,
      "minimum": 1,
      "maximum": 2,
      "type": "RARE"
    },
    {
      "item": 556,
      "minimum": 12,
      "maximum": 36,
      "type": "COMMON"
    },
    {
      "item": 557,
      "minimum": 9,
      "maximum": 9,
      "type": "COMMON"
    },
    {
      "item": 554,
      "minimum": 12,
      "maximum": 12,
      "type": "COMMON"
    },
    {
      "item": 561,
      "minimum": 3,
      "maximum": 3,
      "type": "UNCOMMON"
    },
    {
      "item": 563,
      "minimum": 2,
      "maximum": 2,
      "type": "UNCOMMON"
    },
    {
      "item": 1217,
      "minimum": 1,
      "maximum": 1,
      "type": "UNCOMMON"
    },
    {
      "item": 1313,
      "minimum": 1,
      "maximum": 1,
      "type": "UNCOMMON"
    },
    {
      "item": 995,
      "minimum": 3,
      "maximum": 29,
      "type": "COMMON"
    },
    {
      "item": 235,
      "minimum": 1,
      "maximum": 1,
      "type": "COMMON"
    },
    {
      "item": 239,
      "minimum": 1,
      "maximum": 1,
      "type": "UNCOMMON"
    },
    {
      "item": 231,
      "minimum": 1,
      "maximum": 1,
      "type": "UNCOMMON"
    },
    {
      "item": 225,
      "minimum": 1,
      "maximum": 3,
      "type": "UNCOMMON"
    },
    {
      "item": 227,
      "minimum": 1,
      "maximum": 1,
      "type": "COMMON"
    },
    {
      "item": 167,
      "minimum": 1,
      "maximum": 1,
      "type": "UNCOMMON"
    },
    {
      "item": 13471,
      "minimum": 1,
      "maximum": 1,
      "chance": 25.0,
      "type": "UNCOMMON"
    }
  ]
}