{
  "npc_id": 2918,
  "rare_table": true,
  "drops": [
    {
      "item": 536,
      "minimum": 1,
      "maximum": 1,
      "type": "ALWAYS"
    },
    {
      "item": 1753,
      "minimum": 2,
      "maximum": 2,
      "type": "ALWAYS"
    },
    {
      "item": 11373,
      "minimum": 1,
      "maximum": 1,
      "type": "UNCOMMON"
    },
    {
      "item": 1317,
      "minimum": 1,
      "maximum": 1,
      "type": "UNCOMMON"
    },
    {
      "item": 1215,
      "minimum": 1,
      "maximum": 1,
      "type": "UNCOMMON"
    },
    {
      "item": 1145,
      "minimum": 1,
      "maximum": 1,
      "type": "UNCOMMON"
    },
    {
      "item": 1199,
      "minimum": 1,
      "maximum": 1,
      "type": "UNCOMMON"
    },
    {
      "item": 1113,
      "minimum": 1,
      "maximum": 1,
      "type": "RARE"
    },
    {
      "item": 1163,
      "minimum": 1,
      "maximum": 1,
      "type": "RARE"
    },
    {
      "item": 565,
      "minimum": 15,
      "maximum": 20,
      "type": "COMMON"
    },
    {
      "item": 4699,
      "minimum": 35,
      "maximum": 35,
      "type": "COMMON"
    },
    {
      "item": 4694,
      "minimum": 37,
      "maximum": 37,
      "type": "UNCOMMON"
    },
    {
      "item": 561,
      "minimum": 17,
      "maximum": 17,
      "type": "UNCOMMON"
    },
    {
      "item": 556,
      "minimum": 34,
      "maximum": 34,
      "type": "UNCOMMON"
    },
    {
      "item": 563,
      "minimum": 15,
      "maximum": 15,
      "type": "UNCOMMON"
    },
    {
      "item": 890,
      "minimum": 8,
      "maximum": 8,
      "type": "UNCOMMON"
    },
    {
      "item": 805,
      "minimum": 8,
      "maximum": 8,
      "type": "UNCOMMON"
    },
    {
      "item": 810,
      "minimum": 25,
      "maximum": 25,
      "type": "UNCOMMON"
    },
    {
      "item": 829,
      "minimum": 1,
      "maximum": 1,
      "type": "UNCOMMON"
    },
    {
      "item": 867,
      "minimum": 8,
      "maximum": 8,
      "type": "UNCOMMON"
    },
    {
      "item": 890,
      "minimum": 90,
      "maximum": 90,
      "type": "RARE"
    },
    {
      "item": 199,
      "minimum": 1,
      "maximum": 1,
      "type": "COMMON"
    },
    {
      "item": 201,
      "minimum": 1,
      "maximum": 1,
      "type": "COMMON"
    },
    {
      "item": 203,
      "minimum": 1,
      "maximum": 1,
      "type": "COMMON"
    },
    {
      "item": 205,
      "minimum": 1,
      "maximum": 1,
      "type": "UNCOMMON"
    },
    {
      "item": 207,
      "minimum": 1,
      "maximum": 1,
      "type": "UNCOMMON"
    },
    {
      "item": 209,
      "minimum": 1,
      "maximum": 1,
      "type": "UNCOMMON"
    },
    {
      "item": 211,
      "minimum": 1,
      "maximum": 1,
      "type": "UNCOMMON"
    },
    {
      "item": 213,
      "minimum": 1,
      "maximum": 1,
      "type": "UNCOMMON"
    },
    {
      "item": 215,
      "minimum": 1,
      "maximum": 1,
      "type": "UNCOMMON"
    },
    {
      "item": 2485,
      "minimum": 1,
      "maximum": 1,
      "type": "UNCOMMON"
    },
    {
      "item": 217,
      "minimum": 1,
      "maximum": 1,
      "type": "UNCOMMON"
    },
    {
      "item": 995,
      "minimum": 1,
      "maximum": 1813,
      "type": "COMMON"
    },
    {
      "item": 447,
      "minimum": 5,
      "maximum": 5,
      "type": "UNCOMMON"
    },
    {
      "item": 2011,
      "minimum": 1,
      "maximum": 2,
      "type": "UNCOMMON"
    },
    {
      "item": 13510,
      "minimum": 1,
      "maximum": 1,
      "chance": 28.0,
      "type": "UNCOMMON"
    }
  ]
}